[
  {
    "players_points": {
      "1166": 17.46,
      "4029": 8.9,
      "4039": 0,
      "4137": 12,
      "4149": 7.2,
      "4195": 17,
      "4950": 1.9,
      "5045": 13.2,
      "5844": 11.5,
      "6770": 3.18,
      "6786": 11.7,
      "8155": 15.7,
      "9221": 8,
      "9997": 17.7,
      "KC": 5
    },
    "starters_points": [
      3.18,
      8,
      12,
      1.9,
      11.7,
      11.5,
      13.2,
      7.2,
      17,
      5
    ],
    "starters": [
      "6770",
      "9221",
      "4137",
      "4950",
      "6786",
      "5844",
      "5045",
      "4149",
      "4195",
      "KC"
    ],
    "matchup_id": 5,
    "custom_points": null,
    "roster_id": 1,
    "players": [
      "KC",
      "9997",
      "9221",
      "8155",
      "6786",
      "6770",
      "5844",
      "5045",
      "4950",
      "4195",
      "4149",
      "4137",
      "4039",
      "4029",
      "1166"
    ],
    "points": 90.68
  },
  {
    "players_points": {
      "2309": 6.7,
      "4034": 25.9,
      "4037": 10.1,
      "5095": 5,
      "5185": 6.6,
      "5850": 9.1,
      "5870": 6.46,
      "6783": 0,
      "6826": 9.4,
      "6828": 5.6,
      "6904": 12.5,
      "7553": 6.4,
      "7588": 9.7,
      "8112": 0,
      "BUF": 6
    },
    "starters_points": [
      12.5,
      25.9,
      9.1,
      0,
      6.7,
      6.4,
      0,
      10.1,
      5,
      6
    ],
    "starters": [
      "6904",
      "4034",
      "5850",
      "8112",
      "2309",
      "7553",
      "6783",
      "4037",
      "5095",
      "BUF"
    ],
    "matchup_id": 4,
    "custom_points": null,
    "roster_id": 2,
    "players": [
      "BUF",
      "8112",
      "7588",
      "7553",
      "6904",
      "6828",
      "6826",
      "6783",
      "5870",
      "5850",
      "5185",
      "5095",
      "4037",
      "4034",
      "2309"
    ],
    "points": 81.7
  },
  {
    "players_points": {
      "1264": 5,
      "3163": 14.02,
      "4017": 21.66,
      "4217": 4.9,
      "5967": 22.2,
      "6790": 1.3,
      "6803": 32.9,
      "7526": 11.8,
      "7564": 9.1,
      "8151": 10.7,
      "9226": 0,
      "9488": 4.3,
      "9754": 2.9,
      "9756": 16.1,
      "NYJ": 21
    },
    "starters_points": [
      14.02,
      22.2,
      10.7,
      9.1,
      11.8,
      4.9,
      1.3,
      32.9,
      5,
      21
    ],
    "starters": [
      "3163",
      "5967",
      "8151",
      "7564",
      "7526",
      "4217",
      "6790",
      "6803",
      "1264",
      "NYJ"
    ],
    "matchup_id": 2,
    "custom_points": null,
    "roster_id": 3,
    "players": [
      "NYJ",
      "9756",
      "9754",
      "9488",
      "9226",
      "8151",
      "7564",
      "7526",
      "6803",
      "6790",
      "5967",
      "4217",
      "4017",
      "3163",
      "1264"
    ],
    "points": 132.92
  },
  {
    "players_points": {
      "503": -2,
      "1426": 13.5,
      "2078": 5.7,
      "2216": 18.6,
      "4033": 4.4,
      "4199": 26.7,
      "4866": 9.3,
      "4881": 7.56,
      "4985": 0,
      "6768": 28.14,
      "6794": 24,
      "6806": 11.7,
      "6945": 0.9,
      "7547": 19.1,
      "MIA": 2
    },
    "starters_points": [
      7.56,
      9.3,
      26.7,
      24,
      19.1,
      4.4,
      18.6,
      11.7,
      -2,
      2
    ],
    "starters": [
      "4881",
      "4866",
      "4199",
      "6794",
      "7547",
      "4033",
      "2216",
      "6806",
      "503",
      "MIA"
    ],
    "matchup_id": 3,
    "custom_points": null,
    "roster_id": 4,
    "players": [
      "MIA",
      "7547",
      "6945",
      "6806",
      "6794",
      "6768",
      "503",
      "4985",
      "4881",
      "4866",
      "4199",
      "4033",
      "2216",
      "2078",
      "1426"
    ],
    "points": 121.36
  },
  {
    "players_points": {
      "1466": 0,
      "1479": 14.2,
      "3198": 13.9,
      "3199": 11.1,
      "4040": 7.3,
      "4666": 7,
      "5846": 13.7,
      "5848": 8.7,
      "5987": 13.4,
      "6151": 11.8,
      "7606": 1,
      "8137": 8.6,
      "8160": 11.68,
      "8172": 4.2,
      "PIT": 7
    },
    "starters_points": [
      11.68,
      13.9,
      11.8,
      13.7,
      14.2,
      4.2,
      11.1,
      8.6,
      7,
      7
    ],
    "starters": [
      "8160",
      "3198",
      "6151",
      "5846",
      "1479",
      "8172",
      "3199",
      "8137",
      "4666",
      "PIT"
    ],
    "matchup_id": 4,
    "custom_points": null,
    "roster_id": 5,
    "players": [
      "PIT",
      "8172",
      "8160",
      "8137",
      "7606",
      "6151",
      "5987",
      "5848",
      "5846",
      "4666",
      "4040",
      "3199",
      "3198",
      "1479",
      "1466"
    ],
    "points": 103.18
  },
  {
    "players_points": {
      "3164": 7.3,
      "3271": 7.9,
      "3321": 44.5,
      "4068": 8.5,
      "4227": 8,
      "4984": 12.04,
      "5022": 0,
      "5937": 7.8,
      "6801": 0,
      "6943": 5.2,
      "7528": 5.3,
      "8183": 16.8,
      "8205": 9.4,
      "9505": 0.8,
      "SF": 13
    },
    "starters_points": [
      12.04,
      5.3,
      9.4,
      44.5,
      0,
      0,
      8.5,
      7.8,
      8,
      13
    ],
    "starters": [
      "4984",
      "7528",
      "8205",
      "3321",
      "6801",
      "5022",
      "4068",
      "5937",
      "4227",
      "SF"
    ],
    "matchup_id": 3,
    "custom_points": null,
    "roster_id": 6,
    "players": [
      "SF",
      "9505",
      "8205",
      "8183",
      "7528",
      "6943",
      "6801",
      "5937",
      "5022",
      "4984",
      "4227",
      "4068",
      "3321",
      "3271",
      "3164"
    ],
    "points": 108.54
  },
  {
    "players_points": {
      "96": 0,
      "1266": 11,
      "4046": 20.54,
      "4981": 24.1,
      "4983": 4.5,
      "4988": 16.7,
      "5890": 3.9,
      "5906": 5.5,
      "5927": 5.1,
      "6813": 0,
      "8159": 8.9,
      "8167": 0,
      "9481": 8,
      "9753": 1.1,
      "10236": 6.6,
      "PHI": 15
    },
    "starters_points": [
      20.54,
      16.7,
      1.1,
      24.1,
      4.5,
      6.6,
      8,
      5.1,
      11,
      15
    ],
    "starters": [
      "4046",
      "4988",
      "9753",
      "4981",
      "4983",
      "10236",
      "9481",
      "5927",
      "1266",
      "PHI"
    ],
    "matchup_id": 1,
    "custom_points": null,
    "roster_id": 7,
    "players": [
      "PHI",
      "9753",
      "96",
      "9481",
      "8167",
      "8159",
      "6813",
      "5927",
      "5906",
      "5890",
      "4988",
      "4983",
      "4981",
      "4046",
      "1266",
      "10236"
    ],
    "points": 112.64
  },
  {
    "players_points": {
      "2197": 4.2,
      "2374": 3,
      "2505": 6.6,
      "6938": 8.9,
      "7042": 13,
      "7525": 17.7,
      "7543": 21.4,
      "7591": 15.54,
      "8135": 4.7,
      "8138": 10.3,
      "8146": 14.4,
      "9229": 21.92,
      "9509": 20.3,
      "10229": 11.6,
      "NE": 7
    },
    "starters_points": [
      15.54,
      20.3,
      21.4,
      14.4,
      17.7,
      6.6,
      8.9,
      3,
      13,
      7
    ],
    "starters": [
      "7591",
      "9509",
      "7543",
      "8146",
      "7525",
      "2505",
      "6938",
      "2374",
      "7042",
      "NE"
    ],
    "matchup_id": 5,
    "custom_points": null,
    "roster_id": 8,
    "players": [
      "NE",
      "9509",
      "9229",
      "8146",
      "8138",
      "8135",
      "7591",
      "7543",
      "7525",
      "7042",
      "6938",
      "2505",
      "2374",
      "2197",
      "10229"
    ],
    "points": 127.84
  },
  {
    "players_points": {
      "1433": 8,
      "2449": 26.2,
      "4018": 10.3,
      "4035": 0,
      "4066": 9.9,
      "5859": 14.9,
      "6797": 20.86,
      "7596": 9.2,
      "7608": 11.4,
      "7611": 14.9,
      "8119": 9,
      "8136": 6.9,
      "8144": 19.2,
      "9225": 5.3,
      "BAL": 12
    },
    "starters_points": [
      20.86,
      14.9,
      10.3,
      26.2,
      14.9,
      9.9,
      19.2,
      6.9,
      8,
      12
    ],
    "starters": [
      "6797",
      "7611",
      "4018",
      "2449",
      "5859",
      "4066",
      "8144",
      "8136",
      "1433",
      "BAL"
    ],
    "matchup_id": 1,
    "custom_points": null,
    "roster_id": 9,
    "players": [
      "BAL",
      "9225",
      "8144",
      "8136",
      "8119",
      "7611",
      "7608",
      "7596",
      "6797",
      "5859",
      "4066",
      "4035",
      "4018",
      "2449",
      "1433"
    ],
    "points": 143.16
  },
  {
    "players_points": {
      "2133": 12.6,
      "4663": 26.4,
      "5012": 0,
      "5872": 11.3,
      "5892": 13.4,
      "6819": 23.7,
      "7523": 18.74,
      "7600": 7.3,
      "7839": 3,
      "8129": 6.7,
      "8142": 1.5,
      "8148": 0,
      "8154": 13.6,
      "9228": 9.54,
      "DAL": 40
    },
    "starters_points": [
      18.74,
      26.4,
      6.7,
      12.6,
      11.3,
      7.3,
      23.7,
      13.4,
      3,
      40
    ],
    "starters": [
      "7523",
      "4663",
      "8129",
      "2133",
      "5872",
      "7600",
      "6819",
      "5892",
      "7839",
      "DAL"
    ],
    "matchup_id": 2,
    "custom_points": null,
    "roster_id": 10,
    "players": [
      "DAL",
      "9228",
      "8154",
      "8148",
      "8142",
      "8129",
      "7839",
      "7600",
      "7523",
      "6819",
      "5892",
      "5872",
      "5012",
      "4663",
      "2133"
    ],
    "points": 163.14
  }
]